[{
"scope": "artifacts",
"compactCols":                                [ "objectDefs" ],
"records" : {

"sod.artifact.special.spellbook"            : [ "" ],
"sod.artifact.special.scroll"               : [ "ava0001" ],
"sod.artifact.special.grail"                : [ "" ],

"sod.artifact.battleMachine.catapult"       : [ "" ],
"sod.artifact.battleMachine.ballista"       : [ "" ],
"sod.artifact.battleMachine.ammoCart"       : [ "" ],
"sod.artifact.battleMachine.firstAidTent"   : [ "" ],
"hota.artifact.battleMachine.cannon"        : [ "" ],


"sod.artifact.sword.att2"                   : [ "ava0007" ],
"sod.artifact.sword.att3"                   : [ "ava0008" ],
"sod.artifact.sword.att4"                   : [ "ava0009" ],
"sod.artifact.sword.att5"                   : [ "ava0010" ],
"sod.artifact.sword.att6"                   : [ "ava0011" ],
"hota.artifact.sword.att7"                  : [ "ava0147" ],
"sod.artifact.sword.att12"                  : [ "ava0012" ],

"sod.artifact.shield.def2"                  : [ "ava0013" ],
"sod.artifact.shield.def3"                  : [ "ava0014" ],
"sod.artifact.shield.def4"                  : [ "ava0015" ],
"sod.artifact.shield.def5"                  : [ "ava0016" ],
"sod.artifact.shield.def6"                  : [ "ava0017" ],
"hota.artifact.shield.def7"                 : [ "ava0148" ],
"sod.artifact.shield.def12"                 : [ "ava0018" ],


"sod.artifact.helm.int1"                    : [ "ava0019" ],
"sod.artifact.helm.int2"                    : [ "ava0020" ],
"sod.artifact.helm.int3"                    : [ "ava0021" ],
"sod.artifact.helm.int4"                    : [ "ava0022" ],
"sod.artifact.helm.int5"                    : [ "ava0023" ],
"hota.artifact.helm.int6"                   : [ "ava0150" ],
"sod.artifact.helm.int10"                   : [ "ava0024" ],

"sod.artifact.torso.spl1"                   : [ "ava0025" ],
"sod.artifact.torso.spl2"                   : [ "ava0026" ],
"sod.artifact.torso.spl3"                   : [ "ava0027" ],
"sod.artifact.torso.spl4"                   : [ "ava0028" ],
"sod.artifact.torso.spl5"                   : [ "ava0029" ],
"hota.artifact.torso.spl6"                  : [ "ava0149" ],
"sod.artifact.torso.spl10"                  : [ "ava0030" ],

"sod.artifact.torso.all1"                   : [ "ava0031" ],
"sod.artifact.boots.all2"                   : [ "ava0032" ],
"sod.artifact.neck.all3"                    : [ "ava0033" ],
"sod.artifact.shield.all4"                  : [ "ava0034" ],
"sod.artifact.sword.all5"                   : [ "ava0035" ],
"sod.artifact.helm.all6"                    : [ "ava0036" ],


"sod.artifact.ring.attDef1"                 : [ "ava0037" ],
"sod.artifact.sword.attDef2"                : [ "ava0038" ],
"sod.artifact.shield.attDef3"               : [ "ava0039" ],
"sod.artifact.torso.attDef4"                : [ "ava0040" ],
"sod.artifact.boots.intSpl1"                : [ "ava0041" ],
"sod.artifact.cape.intSpl2"                 : [ "ava0042" ],
"sod.artifact.neck.intSpl3"                 : [ "ava0043" ],
"sod.artifact.helm.intSpl4"                 : [ "ava0044" ],
"sod.artifact.ring.luckMorale1"             : [ "ava0045" ],


"sod.artifact.misc.luck1a"                  : [ "ava0046" ],
"sod.artifact.misc.luck1b"                  : [ "ava0047" ],
"sod.artifact.misc.luck1c"                  : [ "ava0048" ],
"sod.artifact.misc.morale1a"                : [ "ava0049" ],
"sod.artifact.misc.morale1b"                : [ "ava0050" ],
"sod.artifact.misc.morale1c"                : [ "ava0051" ],
"sod.artifact.neck.luckMorale3"             : [ "ava0108" ],


"hota.artifact.misc.unluck1a"               : [ "ava0152" ],
"hota.artifact.misc.unluck1b"               : [ "ava0153" ],
"hota.artifact.misc.unluck2"                : [ "ava0154" ],
"hota.artifact.misc.unmorale1"              : [ "ava0155" ],
"hota.artifact.ring.unmorale1"              : [ "ava0156" ],
"hota.artifact.neck.unmorale2"              : [ "ava0157" ],

"sod.artifact.misc.neutralizeMorale"        : [ "ava0084" ],
"sod.artifact.misc.neutralizeLuck"          : [ "ava0085" ],

"sod.artifact.ring.mp1"                     : [ "ava0070" ],
"sod.artifact.boots.mp1"                    : [ "ava0098" ],
"sod.artifact.neck.mp1"                     : [ "ava0071" ],

"sod.artifact.misc.mana1"                   : [ "ava0073" ],
"sod.artifact.misc.mana2"                   : [ "ava0074" ],
"sod.artifact.misc.mana3"                   : [ "ava0075" ],

"sod.artifact.neck.rounds1"                 : [ "ava0076" ],
"sod.artifact.ring.rounds2"                 : [ "ava0077" ],
"sod.artifact.cape.rounds3"                 : [ "ava0078" ],

"sod.artifact.ring.life1a"                  : [ "ava0094" ],
"sod.artifact.ring.life1b"                  : [ "ava0095" ],
"sod.artifact.misc.life2"                   : [ "ava0096" ],

"sod.artifact.neck.speed1"                  : [ "ava0097" ],
"sod.artifact.ring.speed1"                  : [ "ava0069" ],
"sod.artifact.cape.speed2"                  : [ "ava0099" ],

"sod.artifact.misc.scoutRadius1a"           : [ "ava0052" ],
"sod.artifact.misc.scoutRadius1b"           : [ "ava0053" ],

"sod.artifact.neck.necr1"                   : [ "ava0054" ],
"sod.artifact.cape.necr1"                   : [ "ava0055" ],
"sod.artifact.boots.necr1"                  : [ "ava0056" ],

"sod.artifact.neck.resist1"                 : [ "ava0057" ],
"sod.artifact.cape.resist1"                 : [ "ava0058" ],
"sod.artifact.boots.resist1"                : [ "ava0059" ],

"sod.artifact.misc.archery1"                : [ "ava0060" ],
"sod.artifact.misc.archery2"                : [ "ava0061" ],
"sod.artifact.misc.archery3"                : [ "ava0062" ],

"sod.artifact.misc.eagle1"                  : [ "ava0063" ],
"sod.artifact.misc.eagle2"                  : [ "ava0064" ],
"sod.artifact.misc.eagle3"                  : [ "ava0065" ],

"sod.artifact.neck.diplomacy1"              : [ "ava0066" ],
"sod.artifact.ring.diplomacy2"              : [ "ava0067" ],
"sod.artifact.cape.diplomacy3"              : [ "ava0068" ],

"hota.artifact.misc.interfere"              : [ "ava0162" ],
"hota.artifact.ring.interfere"              : [ "ava0163" ],
"hota.artifact.torso.interfere"             : [ "ava0164" ],

"hota.artifact.boots.pathfind"              : [ "ava0151" ],

"sod.artifact.misc.bookAir"                 : [ "ava0087" ],
"sod.artifact.misc.bookEarth"               : [ "ava0089" ],
"sod.artifact.misc.bookFire"                : [ "ava0086" ],
"sod.artifact.misc.bookWater"               : [ "ava0088" ],

"sod.artifact.helm.spells5"                 : [ "ava0124" ],

"sod.artifact.misc.sphereAir"               : [ "ava0079" ],
"sod.artifact.misc.sphereEarth"             : [ "ava0080" ],
"sod.artifact.misc.sphereFire"              : [ "ava0081" ],
"sod.artifact.misc.sphereWater"             : [ "ava0082" ],

"hota.artifact.cape.noMagic12"              : [ "ava0159" ],
"sod.artifact.cape.noMagic3plus"            : [ "ava0083" ],
"sod.artifact.misc.noMagic"                 : [ "ava0126" ],

"sod.artifact.misc.noDispell"               : [ "ava0092" ],
"sod.artifact.misc.noImmune"                : [ "ava0093" ],
"hota.artifact.ring.noResurrect"            : [ "ava0158" ],

"sod.artifact.neck.protectSpellBers"        : [ "ava0100" ],
"sod.artifact.neck.protectSpellBlind"       : [ "ava0101" ],
"sod.artifact.neck.protectSpellCurse"       : [ "ava0102" ],
"sod.artifact.neck.protectSpellDeathWave"   : [ "ava0103" ],
"sod.artifact.neck.protectSpellKillUndead"  : [ "ava0104" ],
"sod.artifact.neck.protectSpellHypnosis"    : [ "ava0105" ],
"sod.artifact.neck.protectSpellLightning"   : [ "ava0106" ],
"sod.artifact.neck.protectSpellForget"      : [ "ava0107" ],

"sod.artifact.cape.resourceCrystal"         : [ "ava0109" ],
"sod.artifact.ring.resourceGems"            : [ "ava0110" ],
"sod.artifact.misc.resourceCrystal"         : [ "ava0111" ],
"sod.artifact.misc.resourceOre"             : [ "ava0112" ],
"sod.artifact.ring.resourceSulfur"          : [ "ava0113" ],
"sod.artifact.misc.resourceWood"            : [ "ava0114" ],
"sod.artifact.misc.gold1"                   : [ "ava0115" ],
"sod.artifact.misc.gold2"                   : [ "ava0116" ],
"sod.artifact.misc.gold3"                   : [ "ava0117" ],

"sod.artifact.misc.growth2"                 : [ "ava0118" ],
"sod.artifact.misc.growth3"                 : [ "ava0119" ],
"sod.artifact.misc.growth4"                 : [ "ava0120" ],
"sod.artifact.misc.growth5"                 : [ "ava0121" ],
"sod.artifact.misc.growth6"                 : [ "ava0122" ],

"sod.artifact.sword.armag"                  : [ "ava0128" ],

"sod.artifact.cape.spellFly"                : [ "ava0072" ],
"hota.artifact.misc.summon"                 : [ "ava0161" ],
"sod.artifact.boots.spellWalkWater"         : [ "ava0090" ],
"sod.artifact.misc.archeryNoDistance"       : [ "ava0091" ],
"sod.artifact.misc.dragonStuff"             : [ "ava0127" ],
"sod.artifact.misc.noSurrender"             : [ "ava0125" ],
"sod.artifact.helm.boat"                    : [ "ava0123" ],

"sod.artifact.complex.allStat"              : [ "ava0129" ],
"sod.artifact.complex.necro"                : [ "ava0130" ],
"sod.artifact.complex.life"                 : [ "ava0131" ],
"sod.artifact.complex.debuff"               : [ "ava0132" ],
"sod.artifact.complex.growth"               : [ "ava0133" ],
"sod.artifact.complex.immune"               : [ "ava0134" ],
"sod.artifact.complex.freeBolt"             : [ "ava0135" ],
"sod.artifact.complex.fastOnboard"          : [ "ava0136" ],
"sod.artifact.complex.noBowPenalty"         : [ "ava0137" ],
"sod.artifact.complex.manaRegen"            : [ "ava0138" ],
"sod.artifact.complex.spellRounds"          : [ "ava0139" ],
"sod.artifact.complex.resources"            : [ "ava0140" ],

"hota.artifact.complex.diplomacy"           : [ "ava0141" ],
"hota.artifact.complex.resist"              : [ "ava0142" ],
"hota.artifact.complex.buff"                : [ "ava0143" ],
"hota.artifact.complex.gold"                : [ "ava0160" ]

}

},

{
"scope": "units",

"compactCols":                  [ "objectDefs" ],

"records": {
"sod.unit.pikeman"              : [ "avwpike"   ],
"sod.unit.halberdier"           : [ "avwpikx0"  ],
"sod.unit.archer"               : [ "avwlcrs"   ],
"sod.unit.marksman"             : [ "avwhcrs"   ],
"sod.unit.griffin"              : [ "avwgrif"   ],
"sod.unit.royalGriffin"         : [ "avwgrix0"  ],
"sod.unit.swordsman"            : [ "avwswrd0"  ],
"sod.unit.crusader"             : [ "avwswrx0"  ],
"sod.unit.monk"                 : [ "avwmonk"   ],
"sod.unit.zealot"               : [ "avwmonx0"  ],
"sod.unit.cavalier"             : [ "avwcvlr0"  ],
"sod.unit.champion"             : [ "avwcvlx0"  ],
"sod.unit.angel"                : [ "avwangl"   ],
"sod.unit.archangel"            : [ "avwarch"   ],


"sod.unit.centaur"              : [ "avwcent0"  ],
"sod.unit.centaurCaptain"       : [ "avwcenx0"  ],
"sod.unit.dwarf"                : [ "avwdwrf0"  ],
"sod.unit.battleDwarf"          : [ "avwdwrx0"  ],
"sod.unit.woodElf"              : [ "avwelfw0"  ],
"sod.unit.grandElf"             : [ "avwelfx0"  ],
"sod.unit.pegasus"              : [ "avwpega0"  ],
"sod.unit.silverPegasus"        : [ "avwpegx0"  ],
"sod.unit.dendroidGuard"        : [ "avwtree0"  ],
"sod.unit.dendroidSoldier"      : [ "avwtrex0"  ],
"sod.unit.unicorn"              : [ "avwunic0"  ],
"sod.unit.warUnicorn"           : [ "avwunix0"  ],
"sod.unit.greenDragon"          : [ "avwdrag0"  ],
"sod.unit.goldDragon"           : [ "avwdrax0"    ],


"sod.unit.gremlin"             : [  "avwgrem0"  ],
"sod.unit.masterGremlin"       : [  "avwgrex0"  ],
"sod.unit.stoneGargoyle"       : [  "avwgarg0"  ],
"sod.unit.obsidianGargoyle"    : [  "avwgarx0"  ],
"sod.unit.stoneGolem"          : [  "avwgolm0"  ],
"sod.unit.ironGolem"           : [  "avwgolx0"  ],
"sod.unit.mage"                : [  "avwmage0"  ],
"sod.unit.archMage"            : [  "avwmagx0"  ],
"sod.unit.genie"               : [  "avwgeni0"  ],
"sod.unit.masterGenie"         : [  "avwgenx0"  ],
"sod.unit.naga"                : [  "avwnaga0"  ],
"sod.unit.nagaQueen"           : [  "avwnagx0"  ],
"sod.unit.giant"               : [  "avwtitn0"  ],
"sod.unit.titan"               : [  "avwtitx0"  ],


"sod.unit.skeleton"            : [  "avwskel0"  ],
"sod.unit.skeletonWarrior"     : [  "avwskex0"  ],
"sod.unit.walkingDead"         : [  "avwzomb0"  ],
"sod.unit.zombieLord"          : [  "avwzomx0"  ],
"sod.unit.wight"               : [  "avwwigh"   ],
"sod.unit.wraith"              : [  "avwwigx0"  ],
"sod.unit.vampire"             : [  "avwvamp0"  ],
"sod.unit.vampireLord"         : [  "avwvamx0"  ],
"sod.unit.lich"                : [  "avwlich0"  ],
"sod.unit.powerLich"           : [  "avwlicx0"  ],
"sod.unit.blackKnight"         : [  "avwbkni0"  ],
"sod.unit.dreadKnight"         : [  "avwbknx0"  ],
"sod.unit.boneDragon"          : [  "avwbone0"  ],
"sod.unit.ghostDragon"         : [  "avwbonx0"  ],


"sod.unit.troglodyte"          : [  "avwtrog0"  ],
"sod.unit.infernalTroglodyte"  : [  "avwinfr"   ],
"sod.unit.harpy"               : [  "avwharp0"  ],
"sod.unit.harpyHag"            : [  "avwharx0"  ],
"sod.unit.beholder"            : [  "avwbehl0"  ],
"sod.unit.evilEye"             : [  "avwbehx0"  ],
"sod.unit.medusa"              : [  "avwmeds"   ],
"sod.unit.medusaQueen"         : [  "avwmedx0"  ],
"sod.unit.minotaur"            : [  "avwmino"   ],
"sod.unit.minotaurKing"        : [  "avwminx0"  ],
"sod.unit.manticore"           : [  "avwmant0"  ],
"sod.unit.scorpicore"          : [  "avwmanx0"  ],
"sod.unit.redDragon"           : [  "avwrdrg"   ],
"sod.unit.blackDragon"         : [  "avwddrx0"  ],


"sod.unit.imp"                 : [  "avwimp0"   ],
"sod.unit.familiar"            : [  "avwimpx0"  ],
"sod.unit.gog"                 : [  "avwgog0"   ],
"sod.unit.magog"               : [  "avwgogx0"  ],
"sod.unit.hellHound"           : [  "avwhoun0"  ],
"sod.unit.cerberus"            : [  "avwhoux0"  ],
"sod.unit.demon"               : [  "avwdemn0"  ],
"sod.unit.hornedDemon"         : [  "avwdemx0"  ],
"sod.unit.pitFiend"            : [  "avwpitf0"  ],
"sod.unit.pitLord"             : [  "avwpitx0"  ],
"sod.unit.efreet"              : [  "avwefre0"  ],
"sod.unit.efreetSultan"        : [  "avwefrx0"  ],
"sod.unit.devil"               : [  "avwdevl0"  ],
"sod.unit.archDevil"           : [  "avwdevx0"  ],


"sod.unit.gnoll"               : [  "avwgnll0"  ],
"sod.unit.gnollMarauder"       : [  "avwgnlx0"  ],
"sod.unit.lizardman"           : [  "avwlizr"   ],
"sod.unit.lizardWarrior"       : [  "avwlizx0"  ],
"sod.unit.serpentFly"          : [  "avwdfly"   ],
"sod.unit.dragonFly"           : [  "avwdfir"   ],
"sod.unit.basilisk"            : [  "avwbasl"   ],
"sod.unit.greaterBasilisk"     : [  "avwgbas"   ],
"sod.unit.gorgon"              : [  "avwgorg"   ],
"sod.unit.mightyGorgon"        : [  "avwgorx0"  ],
"sod.unit.wyvern"              : [  "avwwyvr"   ],
"sod.unit.wyvernMonarch"       : [  "avwwyvx0"  ],
"sod.unit.hydra"               : [  "avwhydr"   ],
"sod.unit.chaosHydra"          : [  "avwhydx0"  ],


"sod.unit.goblin"              : [  "avwgobl0"  ],
"sod.unit.hobgoblin"           : [  "avwgobx0"  ],
"sod.unit.wolfRider"           : [  "avwwolf0"  ],
"sod.unit.wolfHoboRider"       : [  "avwwolx0"  ],
"sod.unit.orc"                 : [  "avworc0"   ],
"sod.unit.orcChieftain"        : [  "avworcx0"  ],
"sod.unit.ogre"                : [  "avwogre0"  ],
"sod.unit.ogreMage"            : [  "avwogrx0"  ],
"sod.unit.roc"                 : [  "avwroc0"   ],
"sod.unit.thunderbird"         : [  "avwrocx0"  ],
"sod.unit.cyclop"              : [  "avwcycl0"  ],
"sod.unit.cyclopKing"          : [  "avwcycx0"  ],
"sod.unit.behemoth"            : [  "avwbhmt0"  ],
"sod.unit.ancientBehemoth"     : [  "avwbhmx0"  ],


"sod.unit.pixie"               : [  "avwpixie"  ],
"sod.unit.sprite"              : [  "avwsprit"  ],
"sod.unit.airElemental"        : [  "avwelma0"  ],
"sod.unit.stormElemental"      : [  "avwstorm"  ],
"sod.unit.waterElemental"      : [  "avwelmw0"  ],
"sod.unit.iceElemental"        : [  "avwicee"   ],
"sod.unit.fireElemental"       : [  "avwelmf0"  ],
"sod.unit.energyElemental"     : [  "avwnrg"    ],
"sod.unit.earthElemental"      : [  "avwelme0"  ],
"sod.unit.magmaElemental"      : [  "avwstone"  ],
"sod.unit.psychicElemental"    : [  "avwpsye"   ],
"sod.unit.magicElemental"      : [  "avwmagel"  ],
"sod.unit.firebird"            : [  "avwfbird"  ],
"sod.unit.phoenix"             : [  "avwphx"    ],


"hota.unit.nimph"              : [  "avwnimph"  ],
"hota.unit.oceanid"            : [  "avwocean"  ],
"hota.unit.crewMate"           : [  "avwseadg"  ],
"hota.unit.seaMan"             : [  "avwswash"  ],
"hota.unit.pirate"             : [  "avwpirat"  ],
"hota.unit.corsair"            : [  "avwcorsa"  ],
"hota.unit.seawolf"            : [  "avwpr3up"  ],
"hota.unit.stormbird"          : [  "avwassid"  ],
"hota.unit.assid"              : [  "avwassup"  ],
"hota.unit.seaWitch"           : [  "avwpries"  ],
"hota.unit.sorceress"          : [  "avwsorcs"  ],
"hota.unit.nix"                : [  "avwnix"    ],
"hota.unit.nixWarrior"         : [  "avwnixup"  ],
"hota.unit.seaSerpent"         : [  "avwserpe"  ],
"hota.unit.haspid"             : [  "avwhaspi"  ],


"sod.unit.peasant"             : [  "avwpeas"   ],
"sod.unit.halfling"            : [  "avwhalf"   ],
"sod.unit.boar"                : [  "avwboar"   ],
"sod.unit.rogue"               : [  "avwrog"    ],
"sod.unit.nomad"               : [  "avwnomd"   ],
"sod.unit.mummy"               : [  "avwmumy"   ],
"sod.unit.sharpshooter"        : [  "avwsharp"  ],
"sod.unit.goldGolem"           : [  "avwglmg0"  ],
"sod.unit.troll"               : [  "avwtrll"   ],
"sod.unit.diamondGolem"        : [  "avwglmd0"  ],
"sod.unit.enchanter"           : [  "avwench"   ],
"sod.unit.fairieDragon"        : [  "avwfdrg"   ],
"sod.unit.rustDragon"          : [  "avwrust"   ],
"sod.unit.crystalDragon"       : [  "avwcdrg"   ],
"sod.unit.azureDragon"         : [  "avwazure"  ],


"hota.unit.leprechaun"         : [  "avwlepr"   ],
"hota.unit.satyr"              : [  "avwsatyr"  ],
"hota.unit.fangarm"            : [  "avwfngrm"  ],
"hota.unit.steelGolem"         : [  "avwslgl0"  ]

}

},

{
"scope": "resources",

"records": {

"wood"     : {"objectDefs":"avtwood0", "minesDefs": {"m":{"": "avmsawd0", "A": "avmsawg0", "B": "avmsawl0", "C": "avmsawr0", "D": "avmswds0", "E": "avmswsn0", "F": "avmsaws0", "G":  "avmswhl1" }} },
"mercury"  : {"objectDefs":"avtmerc0", "minesDefs": {"m":{"": "avmalch0", "A": "avmalcs0"}} },
"ore"      : {"objectDefs":"avtore0" , "minesDefs": {"m":{"": "avmordr0", "A": "avmords0", "B": "avmore0" , "C": "avmorlv0", "D": "avmorro0", "E": "avmorsb0", "F": "avmorsn0", "G": "avmorsw0", "H": "avmorhl1","K":  "avmorwl1"}} },

"sulfur"   : {"objectDefs":"avtsulf0", "minesDefs": "avmsulf0" },
"crystal"  : {"objectDefs":"avtcrys0", "minesDefs": {"m":{"": "avmcrys0", "A": "avmcrdr0", "B": "avmcrds0", "C": "avmcrgr0", "D": "avmcrrf0", "E": "avmcrsn0", "F": "avmcrsu0", "G": "avmcrsw0", "H": "avmcrvo0", "K": "avmcrhl1", "L": "mntswpcr", "M": "avmcrdn0", "N": "avmcrwl1" }} },
"gems"     : {"objectDefs":"avtgems0", "minesDefs": {"m":{"": "avmgems0", "A": "avmgedr0", "B": "avmgelv0", "C": "avmgerf0", "D": "avmgesd0", "E": "avmgesn0", "F": "avmgehl1", "G": "avmgewl1" }} },

"gold"     : {"objectDefs":"avtgold0", "minesDefs": {"m":{"": "avmgodr0", "A": "avmgogr0", "B": "avmgold0", "C": "avmgorf0", "D": "avmgovo0", "E": "avmgods0", "F": "avmgosb0", "G": "avmgosn0", "H": "avmgosw0", "K": "mntswpgl", "L": "avmgohl1", "M": "avmgddn0", "N": "avmgowl0" }} }
}

},

{
"scope": "mapBanks",

"compactCols":                         [ "objectDefs" ],

"records" : {

"sod.map.crypt"                      : [ { "m":{"": "avxgyds0" , "S": "avxgysn0", "A": "avxgyne0" }} ],
"sod.map.utopia"                     : [  "avsutop0"  ],
"sod.map.derelictShip"               : [  "avadlic0"  ],
"sod.map.shipwreck"                  : [  { "m":{"": "avawrek0", "A": "avawre20" }} ],
"hota.map.blackTower"                : [  { "m":{"": "avblktgr", "S": "avblktsn", "R": "avblktwr" }} ],
"hota.map.mansion"                   : [  "avmnsion"  ],
"hota.map.beholderSanctuary"         : [  "sanct_wt"  ],
"hota.map.templeSea"                 : [  "avsutopw"  ],
"hota.map.churchyard"                : [ { "m":{"": "avcmetry", "A": "avcmetrs", "B": "avcmetrh" }} ],
"sod.map.conservatory"               : [  "avxbnk30"  ],
"sod.map.hive"                       : [  "avxbnk70"  ],
"hota.map.experimentalShop"          : [ { "m":{"": "avxbnk90" , "S": "avxbnk9s" }} ],
"hota.map.wolfRaiderPicket"          : [  "avxbnk80"  ],
"hota.map.vermilionTower"            : [  "avredtwr"  ],
"hota.map.pirateCave"                : [  "hapcave"   ],
"hota.map.ivoryTower"                : [ { "m":{"": "avivtow2", "W": "avivtow1" }} ],

"sod.map.impCache"                   : [ "avxbnk40" ],
"sod.map.dwarvenTreasury"            : [ "avxbnk20" ],
"sod.map.medusaStores"               : [ "avxbnk50" ],
"sod.map.cyclopsStockpile"           : [ "avxbnk10" ],
"sod.map.nagaBank"                   : [ "avxbnk60" ],
"hota.map.spit"                      : [ "avbone02" ],
"hota.map.ruins"                     : [ "avxruins" ]

}

},


{
"scope": "factions",

"compactCols":                         [ "objectDefs" ],

"records" : {

"sod.faction.castle"          : [ {"m": {"":"avccast0", "FORT": "avccasf0", "CIT": "avccasc0", "CAS": "avccasx0", "CAP": "avccasz0"}} ],
"sod.faction.rampart"         : [ {"m": {"":"avcramp0", "FORT": "avcramf0", "CIT": "avcramc0", "CAS": "avcramx0", "CAP": "avcramz0"}} ],
"sod.faction.tower"           : [ {"m": {"":"avctowr0", "FORT": "avctowf0", "CIT": "avctowc0", "CAS": "avctowx0", "CAP": "avctowz0"}} ],
"sod.faction.inferno"         : [ {"m": {"":"avcinft0", "FORT": "avcinff0", "CIT": "avcinfc0", "CAS": "avcinfx0", "CAP": "avcinfz0"}} ],
"sod.faction.necropolis"      : [ {"m": {"":"avcnecr0", "FORT": "avcnecf0", "CIT": "avcnecc0", "CAS": "avcnecx0", "CAP": "avcnecz0"}} ],
"sod.faction.dungeon"         : [ {"m": {"":"avcdung0", "FORT": "avcdunf0", "CIT": "avcdunc0", "CAS": "avcdunx0", "CAP": "avcdunz0"}} ],
"sod.faction.stronghold"      : [ {"m": {"":"avcstro0", "FORT": "avcstrf0", "CIT": "avcstrc0", "CAS": "avcstrx0", "CAP": "avcstrz0"}} ],
"sod.faction.fortress"        : [ {"m": {"":"avcftrt0", "FORT": "avcforf0", "CIT": "avcforc0", "CAS": "avcftrx0", "CAP": "avcforz0"}} ],
"sod.faction.conflux"         : [ {"m": {"":"avchfor0", "FORT": "avchfof0", "CIT": "avchfoc0", "CAS": "avchforx", "CAP": "avchforz"}} ],
"hota.faction.cove"           : [ {"m": {"":"avccove0", "FORT": "avccovf0", "CIT": "avccovc0", "CAS": "avccovx0", "CAP": "avccovz0"}} ]

}
}]

